random_mitype/__init__.py
random_mitype/random_mitype.py
random_mitype/version.py
random_mitype/words/__init__.py
random_mitype/words/english.py
random_mitype-0.1.3.dist-info/LICENSE.md
random_mitype-0.1.3.dist-info/METADATA
random_mitype-0.1.3.dist-info/WHEEL
random_mitype-0.1.3.dist-info/entry_points.txt
random_mitype-0.1.3.dist-info/top_level.txt
random_mitype-0.1.3.dist-info/RECORD
