Metadata-Version: 2.1
Name: random-mitype
Version: 0.1.3
Summary: Generate random typing tests for mitype.
Home-page: https://github.com/RealCyGuy/random-mitype
Author: Cyrus Yip
License: MIT
Platform: UNKNOWN
Classifier: License :: OSI Approved :: MIT License
Classifier: Programming Language :: Python
Classifier: Programming Language :: Python :: 3
Classifier: Programming Language :: Python :: Implementation :: CPython
Classifier: Natural Language :: English
Classifier: Topic :: Terminals
Classifier: Environment :: Console :: Curses
Classifier: Development Status :: 4 - Beta
License-File: LICENSE.md
Requires-Dist: Click
